{
  "naaim": 92.83,
  "naaim_conf": "lag",
  "putcall": 0.59,
  "putcall_conf": "lag",
  "cnnfg": 26.2571428571429,
  "cnnfg_conf": "live",
  "vixterm": 0.915,
  "vixterm_conf": "live",
  "mvrv": 0.2406,
  "mvrv_conf": "live",
  "cryptofg": 12,
  "cryptofg_conf": "live",
  "funding": 0.0044,
  "funding_conf": "live",
  "puell": 0.768,
  "puell_conf": "live",
  "vix": 18.41,
  "breakeven": 2.2,
  "breakeven_conf": "live",
  "wti": 78.94,
  "wti_conf": "live",
  "breadth": 4.25,
  "breadth_conf": "est",
  "rotation": null,
  "rotation_conf": "pend",
  "concentration": 33.8,
  "concentration_conf": "lag",
  "mvrv_p90": 2.569,
  "puell_p90": 1.4108,
  "funding_p90": null,
  "updated": "2026-06-29T15:45:08.109Z",
  "naaim_ts": "2026-06-29T15:45:08.109Z",
  "putcall_ts": "2026-06-29T15:45:08.109Z",
  "cnnfg_ts": "2026-06-29T15:45:08.109Z",
  "vixterm_ts": "2026-06-29T15:45:08.109Z",
  "mvrv_ts": "2026-06-28T21:45:15.438Z",
  "cryptofg_ts": "2026-06-29T15:45:08.109Z",
  "funding_ts": "2026-06-28T21:45:15.438Z",
  "puell_ts": "2026-06-28T21:45:15.438Z",
  "vix_ts": "2026-06-29T15:45:08.109Z",
  "breakeven_ts": "2026-06-29T15:45:08.109Z",
  "wti_ts": "2026-06-29T15:45:08.109Z",
  "breadth_ts": "2026-06-29T15:45:08.109Z",
  "rotation_ts": null,
  "concentration_ts": "2026-06-29T15:45:08.109Z",
  "mvrv_p90_ts": "2026-06-29T15:45:08.109Z",
  "puell_p90_ts": "2026-06-29T15:45:08.109Z",
  "funding_p90_ts": null
}