{
  "naaim": 82.95,
  "naaim_conf": "live",
  "putcall": 0.62,
  "putcall_conf": "live",
  "cnnfg": 37.0571428571429,
  "cnnfg_conf": "live",
  "vixterm": 0.858,
  "vixterm_conf": "live",
  "mvrv": 0.3845,
  "mvrv_conf": "live",
  "cryptofg": 28,
  "cryptofg_conf": "live",
  "funding": 0.0044,
  "funding_conf": "live",
  "puell": 0.837,
  "puell_conf": "live",
  "vix": 16.73,
  "breakeven": 2.24,
  "breakeven_conf": "live",
  "wti": 79.2,
  "wti_conf": "live",
  "breadth": 1.52,
  "breadth_conf": "est",
  "rotation": null,
  "rotation_conf": "pend",
  "concentration": 33.8,
  "concentration_conf": "lag",
  "mvrv_p90": 2.569,
  "puell_p90": 1.4108,
  "funding_p90": null,
  "updated": "2026-07-19T20:30:04.942Z",
  "naaim_ts": "2026-07-19T20:30:04.942Z",
  "putcall_ts": "2026-07-19T20:30:04.942Z",
  "cnnfg_ts": "2026-07-19T20:30:04.942Z",
  "vixterm_ts": "2026-07-19T20:30:04.942Z",
  "mvrv_ts": "2026-07-19T15:32:48.890Z",
  "cryptofg_ts": "2026-07-19T20:30:04.942Z",
  "funding_ts": "2026-06-28T21:45:15.438Z",
  "puell_ts": "2026-07-19T15:32:48.890Z",
  "vix_ts": "2026-07-19T20:30:04.942Z",
  "breakeven_ts": "2026-07-19T20:30:04.942Z",
  "wti_ts": "2026-07-19T20:30:04.942Z",
  "breadth_ts": "2026-07-19T20:30:04.942Z",
  "rotation_ts": null,
  "concentration_ts": "2026-07-19T20:30:04.942Z",
  "mvrv_p90_ts": "2026-07-19T20:30:04.942Z",
  "puell_p90_ts": "2026-07-19T20:30:04.942Z",
  "funding_p90_ts": null
}